setup.py
docker_build/__init__.py
docker_build/_compat.py
docker_build/_docker_driver.py
docker_build/_exec.py
docker_build/_image_builder.py
docker_build/_load_config.py
docker_build/_registry.py
docker_build/_temp.py
docker_build/_vagrant_driver.py
docker_build/cli.py
docker_build.egg-info/PKG-INFO
docker_build.egg-info/SOURCES.txt
docker_build.egg-info/dependency_links.txt
docker_build.egg-info/entry_points.txt
docker_build.egg-info/requires.txt
docker_build.egg-info/top_level.txt