Metadata-Version: 1.0
Name: docker-build
Version: 0.1.2
Summary: Advanced docker image build tool
Home-page: UNKNOWN
Author: Michael Peick
Author-email: docker-build@n-pq.de
License: UNKNOWN
Platform: UNKNOWN
